librouteros/__init__.py
librouteros/api.py
librouteros/connections.py
librouteros/exceptions.py
librouteros/login.py
librouteros/protocol.py
librouteros/query.py
librouteros/types.py
librouteros-3.4.0.dist-info/LICENSE
librouteros-3.4.0.dist-info/METADATA
librouteros-3.4.0.dist-info/WHEEL
librouteros-3.4.0.dist-info/RECORD
